netlink/sharepoint/__init__.py
netlink/sharepoint/_item.py
netlink/sharepoint/_list.py
netlink/sharepoint/_site.py
netlink/sharepoint/cli.py
netlink_sharepoint-0.0.6.dist-info/entry_points.txt
netlink_sharepoint-0.0.6.dist-info/WHEEL
netlink_sharepoint-0.0.6.dist-info/METADATA
netlink_sharepoint-0.0.6.dist-info/RECORD
